rumblelib.py
rumblelib_test-0.1.0.dist-info/LICENSE
rumblelib_test-0.1.0.dist-info/METADATA
rumblelib_test-0.1.0.dist-info/WHEEL
rumblelib_test-0.1.0.dist-info/top_level.txt
rumblelib_test-0.1.0.dist-info/RECORD
