Metadata-Version: 2.1
Name: rumblelib-test
Version: 0.1.0
Home-page: https://github.com/robot-rumble/logic/tree/master/lang-runners/python/stdlib
Author: Robot Rumble Team
Author-email: antonoutkine@gmail.com
License: GNU GPL3
Project-URL: Documentation, https://rr-docs.readthedocs.io/en/latest/api.html
Classifier: License :: OSI Approved :: GNU General Public License v3 (GPLv3)
License-File: LICENSE
